taming/__init__.py
taming/lr_scheduler.py
taming/main.py
taming/util.py
taming/data/__init__.py
taming/data/ade20k.py
taming/data/base.py
taming/data/coco.py
taming/data/custom.py
taming/data/faceshq.py
taming/data/imagenet.py
taming/data/sflckr.py
taming/data/utils.py
taming/models/__init__.py
taming/models/cond_transformer.py
taming/models/vqgan.py
taming/modules/__init__.py
taming/modules/util.py
taming/modules/diffusionmodules/__init__.py
taming/modules/diffusionmodules/model.py
taming/modules/discriminator/__init__.py
taming/modules/discriminator/model.py
taming/modules/losses/__init__.py
taming/modules/losses/lpips.py
taming/modules/losses/segmentation.py
taming/modules/losses/vqperceptual.py
taming/modules/misc/__init__.py
taming/modules/misc/coord.py
taming/modules/transformer/__init__.py
taming/modules/transformer/mingpt.py
taming/modules/transformer/permuter.py
taming/modules/vqvae/__init__.py
taming/modules/vqvae/quantize.py
taming_transformers_rom1504-0.0.6.dist-info/METADATA
taming_transformers_rom1504-0.0.6.dist-info/WHEEL
taming_transformers_rom1504-0.0.6.dist-info/top_level.txt
taming_transformers_rom1504-0.0.6.dist-info/RECORD
