Metadata-Version: 1.0
Name: taming-transformers-rom1504
Version: 0.0.6
Summary: Taming Transformers for High-Resolution Image Synthesis
Home-page: UNKNOWN
Author: UNKNOWN
Author-email: UNKNOWN
License: UNKNOWN
Platform: UNKNOWN
